fimserve/__init__.py
fimserve/datadownload.py
fimserve/intersectedHUC.py
fimserve/runFIM.py
fimserve/vizualizationFIM.py
fimserve/FIMsubset/__init__.py
fimserve/FIMsubset/shpsubset.py
fimserve/FIMsubset/xycoord.py
fimserve/enhancement_withSM/SM_prediction.py
fimserve/enhancement_withSM/SM_preprocess.py
fimserve/enhancement_withSM/__init__.py
fimserve/enhancement_withSM/building_exposure.py
fimserve/enhancement_withSM/interactS3.py
fimserve/enhancement_withSM/pop_exposure.py
fimserve/enhancement_withSM/preprocessFIM.py
fimserve/enhancement_withSM/surrogate_model.py
fimserve/enhancement_withSM/utlis.py
fimserve/fimevaluation/__init__.py
fimserve/fimevaluation/fims_setup.py
fimserve/fimevaluation/run_fimeval.py
fimserve/fimevaluation/utilis.py
fimserve/plot/__init__.py
fimserve/plot/comparestreamflow.py
fimserve/plot/nwmfid.py
fimserve/plot/src.py
fimserve/plot/usgs.py
fimserve/plot/usgsandfid.py
fimserve/statistics/__init__.py
fimserve/statistics/calculatestatistics.py
fimserve/streamflowdata/__init__.py
fimserve/streamflowdata/forecasteddata.py
fimserve/streamflowdata/geoglows.py
fimserve/streamflowdata/nwmretrospective.py
fimserve/streamflowdata/usgsdata.py
fimserve-0.1.92.dist-info/licenses/LICENSE
fimserve-0.1.92.dist-info/METADATA
fimserve-0.1.92.dist-info/WHEEL
fimserve-0.1.92.dist-info/top_level.txt
fimserve-0.1.92.dist-info/RECORD
