Metadata-Version: 2.4
Name: fimserve
Version: 0.1.92
Summary: Framework which is developed with the purpose of quickly generating Flood Inundation Maps (FIM) for emergency response and risk assessment. It is developed under Surface Dynamics Modeling Lab (SDML).
Author-email: Supath Dhital <sdhital@crimson.ua.edu>
Maintainer-email: Supath Dhital <sdhital@crimson.ua.edu>
License: GPL-3.0
Project-URL: Homepage, https://github.com/sdmlua/FIMserv
Project-URL: Repository, https://github.com/sdmlua/FIMserv
Project-URL: Issues, https://github.com/sdmlua/FIMserv/issues
Requires-Python: <3.13,>=3.10
License-File: LICENSE
Requires-Dist: teehr==0.5.0
Requires-Dist: geemap>=0.35.1
Requires-Dist: pyarrow>=15.0.2
Requires-Dist: numpy>=2.0.0
Requires-Dist: netcdf4>=1.7.2
Requires-Dist: fiona>=1.10.1
Requires-Dist: utils>=1.0.2
Requires-Dist: matplotlib>=3.9.2
Requires-Dist: awscli>=1.42.0
Requires-Dist: boto3>=1.40.0
Requires-Dist: numba==0.60.0
Requires-Dist: bottleneck>=1.3.6
Requires-Dist: localtileserver>=0.10.5
Requires-Dist: tqdm>=4.67.0
Requires-Dist: scipy>=1.14.1
Requires-Dist: aiohttp>=3.12.14
Requires-Dist: scikit-learn>=1.5.2
Requires-Dist: tabulate>=0.9.0
Requires-Dist: nodejs-bin>=18.4.0a4
Requires-Dist: ipykernel>=6.17.1
Requires-Dist: beautifulsoup4>=4.12.3
Requires-Dist: python-dotenv>=1.0.1
Requires-Dist: jupyter>=1.1.1
Requires-Dist: notebook>=6.5.7
Requires-Dist: geocube<=0.7.1
Requires-Dist: geopandas>=0.14.3
Requires-Dist: fimeval>=0.1.56
Provides-Extra: dev
Requires-Dist: pytest<8.4,>=8.3; extra == "dev"
Requires-Dist: sphinx<7.0; extra == "dev"
Requires-Dist: sphinx-autobuild>=2024.10.3; extra == "dev"
Requires-Dist: black; extra == "dev"
Provides-Extra: sm
Requires-Dist: torch>=2.3.0; extra == "sm"
Requires-Dist: pytorch-lightning<3,>=2.2; extra == "sm"
Requires-Dist: torchmetrics<2,>=1.3; extra == "sm"
Requires-Dist: msfootprint>=0.1.31; extra == "sm"
Dynamic: license-file
